agora_gw/__init__.py
agora_gw/metadata.json
agora_gw/data/__init__.py
agora_gw/data/graph.py
agora_gw/data/repository.py
agora_gw/data/sparql.py
agora_gw/ecosystem/__init__.py
agora_gw/ecosystem/description.py
agora_gw/ecosystem/discover.py
agora_gw/ecosystem/serialize.py
agora_gw/gateway/__init__.py
agora_gw/gateway/abstract.py
agora_gw/gateway/add.py
agora_gw/gateway/delete.py
agora_gw/gateway/discover.py
agora_gw/gateway/eco.py
agora_gw/gateway/errors.py
agora_gw/misc/__init__.py
agora_gw/misc/utils.py
agora_gw/server/__init__.py
agora_gw/server/api.py
agora_gw/server/app.py
agora_gw/server/client.py
agora_gw/server/dispatch.py
agora_gw/server/worker.py
agora_gw-0.1.24.data/scripts/gw
agora_gw-0.1.24.dist-info/LICENSE
agora_gw-0.1.24.dist-info/METADATA
agora_gw-0.1.24.dist-info/WHEEL
agora_gw-0.1.24.dist-info/top_level.txt
agora_gw-0.1.24.dist-info/RECORD
