Metadata-Version: 2.1
Name: agora-gw
Version: 0.1.24
Summary: A semantic gateway for the Web of Things
Home-page: https://github.com/fserena/agora-gw
Author: Fernando Serena
Author-email: kudhmud@gmail.com
License: Apache 2
Download-URL: https://github.com/oeg-upm/agora-gw/tarball/0.1.24
Keywords: agora,discovery,linked data
Platform: UNKNOWN
Requires-Dist: Flask
Requires-Dist: Flask-Cache
Requires-Dist: gunicorn
Requires-Dist: Flask-Negotiate
Requires-Dist: futures
Requires-Dist: requests
Requires-Dist: urllib3
Requires-Dist: rdflib (==4.2.1)
Requires-Dist: SPARQLWrapper
Requires-Dist: python-dateutil
Requires-Dist: pyld
Requires-Dist: rdflib-jsonld
Requires-Dist: jsonpath-rw
Requires-Dist: shortuuid
Requires-Dist: agora-py
Requires-Dist: agora-wot
Requires-Dist: redis-simple-cache
Requires-Dist: networkx (>=2.0)
